zip2np/__init__.py
zip2np/config.txt
zip2np/edem.py
zip2np-0.1.4.dist-info/LICENSE
zip2np-0.1.4.dist-info/METADATA
zip2np-0.1.4.dist-info/WHEEL
zip2np-0.1.4.dist-info/top_level.txt
zip2np-0.1.4.dist-info/RECORD
